AUTHORS.md
CHANGELOG.md
CONTRIBUTING.md
LICENSE
MANIFEST.in
README.md
pyproject.toml
setup.py
docs/.readthedocs.yml
docs/Makefile
docs/conf.py
docs/design.rst
docs/index.rst
docs/intro.rst
docs/make.bat
docs/miniff.rst
docs/modules.rst
docs/requirements.txt
docs/using.rst
miniff/__init__.py
miniff/__main__.py
miniff/_potentials.c
miniff/_potentials.pyx
miniff/_util.c
miniff/_util.pyx
miniff/ewald.py
miniff/kernel.py
miniff/ml.py
miniff/ml_util.py
miniff/potentials.py
miniff/presentation.py
miniff/test_ewald.py
miniff/test_kernel.py
miniff/test_main.py
miniff/test_ml.py
miniff/test_ml_util.py
miniff/test_potentials.py
miniff/test_samples.py
miniff/test_units.py
miniff/test_util.py
miniff/units.py
miniff/util.py
miniff/version.py
miniff.egg-info/PKG-INFO
miniff.egg-info/SOURCES.txt
miniff.egg-info/dependency_links.txt
miniff.egg-info/requires.txt
miniff.egg-info/top_level.txt
resources/potentials.json
templates/potential-2-g.pyx
templates/potential-2.pyx
templates/potential-3-g.pyx
templates/potential-3.pyx
templates/potential-ewald-k-c.pyx
templates/potential-ewald-k-g.pyx
templates/potential-ewald-k.pyx
templates/potential-ewald-r-c.pyx
templates/potentials.pyx