Metadata-Version: 2.1
Name: miniff
Version: 0.1.4
Summary: A minimal implementation of force fields
Home-page: UNKNOWN
Author: miniff contributors
Author-email: gpulkin@gmail.com
License: UNKNOWN
Platform: UNKNOWN
